galacticatipsy/__init__.py
galacticatipsy/test1.py
galacticatipsy/test2.py
galacticatipsy-0.0.5.dist-info/METADATA
galacticatipsy-0.0.5.dist-info/WHEEL
galacticatipsy-0.0.5.dist-info/top_level.txt
galacticatipsy-0.0.5.dist-info/RECORD
