Metadata-Version: 2.1
Name: galacticatipsy
Version: 0.0.5
Summary: Package for Galactica Tipsy
Home-page: http://www.star.uclan.ac.uk/~sgough-kelly/galactica/
Author: Steven Gough-Kelly
Author-email: steventgk@gmail.com
License: LGPL
Platform: UNKNOWN
Classifier: Development Status :: 1 - Planning
Classifier: Intended Audience :: Science/Research
Classifier: License :: OSI Approved :: GNU Library or Lesser General Public License (LGPL)
Classifier: Operating System :: OS Independent
Classifier: Programming Language :: Python :: 3
Classifier: Programming Language :: Python :: 3.4
Classifier: Programming Language :: Python :: 3.5
Classifier: Programming Language :: Python :: 3.8
Requires-Dist: numpy
Requires-Dist: matplotlib
